{
  "timestamp": "2026-02-18T09:47:10.229Z",
  "total": 2613,
  "passed": 2600,
  "warnings": 0,
  "issues": 13,
  "issueDetails": [
    {
      "id": "g5-de-009",
      "issues": [
        "數學錯誤: 長方形面積: 應=300, 實=316.2"
      ],
      "content": "一塊地長 25.5 公尺，寬 12.4 公尺，面積是多少平方公尺？"
    },
    {
      "id": "g5-ar-009",
      "issues": [
        "數學錯誤: 長方形面積: 應=96, 實=48"
      ],
      "content": "把一個長方形（長 12 公分，寬 8 公分）沿對角線剪開，得到的三角形面積是多少平方公分？"
    },
    {
      "id": "g5-av-206",
      "issues": [
        "數學錯誤: 長方形面積: 應=48, 實=24"
      ],
      "content": "把長方形（長 8 寬 6）對角線連接，得到的三角形面積是多少？"
    },
    {
      "id": "g5-ts-302",
      "issues": [
        "數學錯誤: 速度問題: 應=160, 實=200"
      ],
      "content": "火車時速 80 公里，2 小時 30 分鐘能行多少公里？"
    },
    {
      "id": "g5-gf-510",
      "issues": [
        "數學錯誤: 三角形面積: 應=24, 實=3"
      ],
      "content": "把一個底 8、高 6 的三角形拼成一個面積相等的平行四邊形，底是 8，高是多少？"
    },
    {
      "id": "g6-cy-006",
      "issues": [
        "數學錯誤: 圓面積: 應≈153.9, 實=308"
      ],
      "content": "把一個底面半徑 7 公分、高 10 公分的圓柱橫切成 2 個相等的圓柱，表面積增加了多少平方公分？（"
    },
    {
      "id": "g6-cy-009",
      "issues": [
        "數學錯誤: 圓面積: 應≈113.1, 實=376.8"
      ],
      "content": "把半徑 6 公分、高 10 公分的圓柱放入長方體水箱中，水面上升 3 公分，水箱底面積是多少平方公分"
    },
    {
      "id": "g6-ci-104",
      "issues": [
        "數學錯誤: 圓面積: 應≈314.2, 實=200.96"
      ],
      "content": "兩個同心圓，大圓半徑 10 公分，小圓半徑 6 公分，圓環面積是多少？（π=3.14）"
    },
    {
      "id": "g6-vo-109",
      "issues": [
        "數學錯誤: 圓面積: 應≈113.1, 實=192"
      ],
      "content": "把一個底面半徑 6 公分、高 8 公分的圓柱沿底面直徑切成兩半，增加的表面積是多少？（π=3.14）"
    },
    {
      "id": "g6-cb-306",
      "issues": [
        "數學錯誤: 圓面積: 應≈201.1, 實=122.46"
      ],
      "content": "圓環外圓半徑 8 公分，內圓半徑 5 公分，面積是多少？（π=3.14）"
    },
    {
      "id": "g6-gf-505",
      "issues": [
        "數學錯誤: 圓面積: 應≈113.1, 實=226.08"
      ],
      "content": "把一個底面半徑 6、高 12 的圓柱橫切成兩個相等的圓柱，表面積增加多少？（π=3.14）"
    },
    {
      "id": "g6-sp-633",
      "issues": [
        "數學錯誤: 圓面積: 應≈314.2, 實=200.96"
      ],
      "content": "圓環外圓半徑 10，內圓半徑 6，面積是？（π=3.14）"
    },
    {
      "id": "ps2-4040",
      "issues": [
        "數學錯誤: 圓面積: 應≈78.5, 實=471"
      ],
      "content": "圓柱底面半徑 5、高 10，表面積約多少？（π取3.14）"
    }
  ],
  "warningDetails": [],
  "issueTypes": {
    "數學錯誤": 13
  }
}